LICENSE
README.md
setup.py
lightning_module_enhanced/__init__.py
lightning_module_enhanced/active_run_mixin.py
lightning_module_enhanced/lme.py
lightning_module_enhanced/logger.py
lightning_module_enhanced/loss.py
lightning_module_enhanced/multi_trainer.py
lightning_module_enhanced/trainable_module.py
lightning_module_enhanced/utils.py
lightning_module_enhanced.egg-info/PKG-INFO
lightning_module_enhanced.egg-info/SOURCES.txt
lightning_module_enhanced.egg-info/dependency_links.txt
lightning_module_enhanced.egg-info/requires.txt
lightning_module_enhanced.egg-info/top_level.txt
lightning_module_enhanced/callbacks/__init__.py
lightning_module_enhanced/callbacks/metadata_callback.py
lightning_module_enhanced/callbacks/plot_callback.py
lightning_module_enhanced/callbacks/plot_metrics.py
lightning_module_enhanced/callbacks/remove_previous_train_artifacts.py
lightning_module_enhanced/metrics/__init__.py
lightning_module_enhanced/metrics/callable_core_metric.py
lightning_module_enhanced/metrics/core_metric.py
lightning_module_enhanced/metrics/mean_iou.py
lightning_module_enhanced/metrics/multi_class_accuracy.py
lightning_module_enhanced/metrics/multi_class_confusion_matrix.py
lightning_module_enhanced/metrics/multi_class_f1_score.py
lightning_module_enhanced/metrics/stub_metric.py
lightning_module_enhanced/schedulers/__init__.py
lightning_module_enhanced/schedulers/cycles_list_lr.py
lightning_module_enhanced/schedulers/min_max_lr.py
lightning_module_enhanced/schedulers/reduce_lr_on_plateau_with_burn_in.py